zipr/__init__.py
zipr/_modidx.py
zipr/_tmp.py
zipr/core.py
zipr-0.0.2.dist-info/LICENSE
zipr-0.0.2.dist-info/METADATA
zipr-0.0.2.dist-info/WHEEL
zipr-0.0.2.dist-info/entry_points.txt
zipr-0.0.2.dist-info/top_level.txt
zipr-0.0.2.dist-info/RECORD
