Metadata-Version: 2.1
Name: zipr
Version: 0.0.2
Summary: zipr
Home-page: https://github.com/dsm-72/zipr
Author: dsm-72
Author-email: sumner.magruder@yale.edu
License: Apache Software License 2.0
Keywords: zipr mount load package library mounter loader inspect import importlib pkg module
Classifier: Development Status :: 4 - Beta
Classifier: Intended Audience :: Developers
Classifier: Natural Language :: English
Classifier: Programming Language :: Python :: 3.11
Classifier: License :: OSI Approved :: Apache Software License
Requires-Python: >=3.11
License-File: LICENSE
Provides-Extra: dev
